otpylib_logger/__init__.py
otpylib_logger/api.py
otpylib_logger/atoms.py
otpylib_logger/boundaries.py
otpylib_logger/core.py
otpylib_logger/data.py
otpylib_logger/lifecycle.py
otpylib_logger/handlers/__init__.py
otpylib_logger/handlers/console.py
otpylib_logger/handlers/file.py
otpylib_logger-0.2.8.dist-info/METADATA
otpylib_logger-0.2.8.dist-info/WHEEL
otpylib_logger-0.2.8.dist-info/top_level.txt
otpylib_logger-0.2.8.dist-info/RECORD
